Metadata-Version: 2.1
Name: SpotifyLinuxOpen
Version: 0.1.0
Summary: A simple cli-utility that allows you to open 'open.spotify.com' in the Spotify desktop client on Linux
Home-page: https://git.orudo.ru/trueold89/SpotifyLinuxOpen
Author: trueold89
Author-email: trueold89@orudo.ru
